orbits/__init__.py
orbits/kernel.py
orbits/model.py
orbits/params.py
orbits/plots.py
orbits/prior.py
orbits/utils.py
orbits-0.1.0.dist-info/LICENSE
orbits-0.1.0.dist-info/METADATA
orbits-0.1.0.dist-info/WHEEL
orbits-0.1.0.dist-info/top_level.txt
orbits-0.1.0.dist-info/RECORD
