Metadata-Version: 2.1
Name: orbits
Version: 0.1.0
Summary: Orbit fitting with PyMC3 and exoplanet
Home-page: https://github.com/vandalt/orbits
Author: Thomas Vandal
Author-email: thomasvandal@hotmail.com
License: MIT License
Platform: UNKNOWN
License-File: LICENSE
Requires-Dist: pymc3
Requires-Dist: celerite2
Requires-Dist: aesara-theano-fallback
Requires-Dist: pymc3-ext
Requires-Dist: exoplanet
Requires-Dist: matplotlib
Requires-Dist: numpy
Requires-Dist: pyyaml
Requires-Dist: corner
Provides-Extra: dev
Requires-Dist: ipython ; extra == 'dev'
Requires-Dist: jupytext ; extra == 'dev'
Requires-Dist: black ; extra == 'dev'
Requires-Dist: isort ; extra == 'dev'
Requires-Dist: flake8 ; extra == 'dev'
Requires-Dist: pandas ; extra == 'dev'
